pcfrv/search_school.py
pcfrv/search_school.pyi
pcfrv/timetable.py
pcfrv/timetable.pyi
pcfrv-0.2.12.dist-info/METADATA
pcfrv-0.2.12.dist-info/WHEEL
pcfrv-0.2.12.dist-info/top_level.txt
pcfrv-0.2.12.dist-info/RECORD
