Metadata-Version: 2.2
Name: pcfrv
Version: 0.2.12
Summary: PyComcigan Forked with Runtime Validation
Requires-Python: >=3.9
Requires-Dist: fake-useragent==2.0.3
Requires-Dist: httpx==0.28.1
Requires-Dist: pydantic==2.10.6
